[
  {
    "number":"222",
    "subject":"URGENT: Phase 1.1: Modification on electrical ductbank proposal",
    "due_date":1760313600000,
    "days_late":0,
    "ball_in_court":"Aggeliki Spetsieris (DEC US)",
    "days_in_court":"0",
    "anchor_date":"2025-10-06 10:34:00",
    "link":"https:\/\/us02.procore.com\/598134325936838\/project\/rfi\/show\/598134326923683",
    "last_reminder_date":"N\/A",
    "mailto_reminder":"mailto:?to=aggeliki%40domacoencocorp.com&cc=aggeliki%40domacoencocorp.com%3Bkeith%40domacoencocorp.com%3Bigor%40domacoencocorp.com%3Bbbidder%40domacoencocorp.com%3Bgsilvat%40domacoencocorp.com%3Brjustice%40domacoencocorp.com&subject=RFI%20222%3A%20URGENT%3A%20Phase%201.1%3A%20Modification%20on%20electrical%20ductbank%20proposal%20%E2%80%94%20Response%20requested&body=Hi%20Aggeliki%2C%0A%0AReminder%20for%20this%20RFI.%20It%20has%20been%20in%20your%20court%20for%200%20business%20day%28s%29.%0ADue%20date%3A%202025-10-13%0A%0ARFI%20link%3A%20https%3A%2F%2Fus02.procore.com%2F598134325936838%2Fproject%2Frfi%2Fshow%2F598134326923683%0A%0APlease%20let%20us%20know%20if%20any%20additional%20details%20are%20needed.%0A%0AThank%20you%2C&font=Aptos&color=black"
  },
  {
    "number":"220",
    "subject":"Phase 1.1: Generator Cover Plate",
    "due_date":1759968000000,
    "days_late":0,
    "ball_in_court":"Chris Cowl (Adag Group inc.), Nikoloas Karayiannis (5C Data Centers)",
    "days_in_court":"2",
    "anchor_date":"2025-10-02 13:36:00",
    "link":"https:\/\/us02.procore.com\/598134325936838\/project\/rfi\/show\/598134326915603",
    "last_reminder_date":"N\/A",
    "mailto_reminder":"mailto:?to=chrisc%40adaggroup.com%3Bnkarayiannis%405cdatacenters.com&cc=aggeliki%40domacoencocorp.com%3Bkeith%40domacoencocorp.com%3Bigor%40domacoencocorp.com%3Bbbidder%40domacoencocorp.com%3Bgsilvat%40domacoencocorp.com%3Brjustice%40domacoencocorp.com&subject=RFI%20220%3A%20Phase%201.1%3A%20Generator%20Cover%20Plate%20%E2%80%94%20Response%20requested&body=Hi%20Chris%20and%20Nikoloas%2C%0A%0AReminder%20for%20this%20RFI.%20It%20has%20been%20in%20your%20court%20for%202%20business%20day%28s%29.%0ADue%20date%3A%202025-10-09%0A%0ARFI%20link%3A%20https%3A%2F%2Fus02.procore.com%2F598134325936838%2Fproject%2Frfi%2Fshow%2F598134326915603%0A%0APlease%20let%20us%20know%20if%20any%20additional%20details%20are%20needed.%0A%0AThank%20you%2C&font=Aptos&color=black"
  },
  {
    "number":"217",
    "subject":"URGENT: Phase 1.1 \/ 1.2\/ 1.3: Generator Anchorage",
    "due_date":1759968000000,
    "days_late":0,
    "ball_in_court":"Chris Cowl (Adag Group inc.), Mesrob Arsenian (Adag Group inc.)",
    "days_in_court":"1",
    "anchor_date":"2025-10-03 08:30:00",
    "link":"https:\/\/us02.procore.com\/598134325936838\/project\/rfi\/show\/598134326916254",
    "last_reminder_date":"N\/A",
    "mailto_reminder":"mailto:?to=chrisc%40adaggroup.com%3Bmesrob%40adaggroup.com&cc=aggeliki%40domacoencocorp.com%3Bkeith%40domacoencocorp.com%3Bigor%40domacoencocorp.com%3Bbbidder%40domacoencocorp.com%3Bgsilvat%40domacoencocorp.com%3Brjustice%40domacoencocorp.com&subject=RFI%20217%3A%20URGENT%3A%20Phase%201.1%20%2F%201.2%2F%201.3%3A%20Generator%20Anchorage%20%E2%80%94%20Response%20requested&body=Hi%20Chris%20and%20Mesrob%2C%0A%0AReminder%20for%20this%20RFI.%20It%20has%20been%20in%20your%20court%20for%201%20business%20day%28s%29.%0ADue%20date%3A%202025-10-09%0A%0ARFI%20link%3A%20https%3A%2F%2Fus02.procore.com%2F598134325936838%2Fproject%2Frfi%2Fshow%2F598134326916254%0A%0APlease%20let%20us%20know%20if%20any%20additional%20details%20are%20needed.%0A%0AThank%20you%2C&font=Aptos&color=black"
  },
  {
    "number":"215",
    "subject":"URGENT: Phase 1.1: RTU\/ MAU and ATS Installation",
    "due_date":1759708800000,
    "days_late":0,
    "ball_in_court":"Chris Cowl (Adag Group inc.), Mouhamadou Ndoye (Exp Global Inc.), Theo Tuaillon (MA-TH inc.), Tristan Lefebvre (MA-TH inc.)",
    "days_in_court":"0",
    "anchor_date":"2025-10-06 11:17:00",
    "link":"https:\/\/us02.procore.com\/598134325936838\/project\/rfi\/show\/598134326902618",
    "last_reminder_date":"N\/A",
    "mailto_reminder":"mailto:?to=chrisc%40adaggroup.com%3Bmouhamadou.ndoye%40exp.com%3Bt.tuaillon%40ma-th.ca%3Bt.lefebvre%40ma-th.ca&cc=aggeliki%40domacoencocorp.com%3Bkeith%40domacoencocorp.com%3Bigor%40domacoencocorp.com%3Bbbidder%40domacoencocorp.com%3Bgsilvat%40domacoencocorp.com%3Brjustice%40domacoencocorp.com&subject=RFI%20215%3A%20URGENT%3A%20Phase%201.1%3A%20RTU%2F%20MAU%20and%20ATS%20Installation%20%E2%80%94%20Response%20requested&body=Hi%20Chris%2C%20Mouhamadou%2C%20Theo%2C%20and%20Tristan%2C%0A%0AReminder%20for%20this%20RFI.%20It%20has%20been%20in%20your%20court%20for%200%20business%20day%28s%29.%0ADue%20date%3A%202025-10-06%0A%0ARFI%20link%3A%20https%3A%2F%2Fus02.procore.com%2F598134325936838%2Fproject%2Frfi%2Fshow%2F598134326902618%0A%0APlease%20let%20us%20know%20if%20any%20additional%20details%20are%20needed.%0A%0AThank%20you%2C&font=Aptos&color=black"
  },
  {
    "number":"214",
    "subject":"Substation: Underground Power Busway Interference",
    "due_date":1759363200000,
    "days_late":2,
    "ball_in_court":"Peter Frasca (Symtech Innovations USA Inc.)",
    "days_in_court":"6",
    "anchor_date":"2025-09-26 14:31:00",
    "link":"https:\/\/us02.procore.com\/598134325936838\/project\/rfi\/show\/598134326896402",
    "last_reminder_date":"N\/A",
    "mailto_reminder":"mailto:?to=peter.frasca%40symtech.com&cc=aggeliki%40domacoencocorp.com%3Bkeith%40domacoencocorp.com%3Bigor%40domacoencocorp.com%3Bbbidder%40domacoencocorp.com%3Bgsilvat%40domacoencocorp.com%3Brjustice%40domacoencocorp.com&subject=RFI%20214%3A%20Substation%3A%20Underground%20Power%20Busway%20Interference%20%E2%80%94%20Response%20requested&body=Hi%20Peter%2C%0A%0AReminder%20for%20this%20RFI.%20It%20has%20been%20in%20your%20court%20for%206%20business%20day%28s%29.%0ADue%20date%3A%202025-10-02%0A%0ARFI%20link%3A%20https%3A%2F%2Fus02.procore.com%2F598134325936838%2Fproject%2Frfi%2Fshow%2F598134326896402%0A%0APlease%20let%20us%20know%20if%20any%20additional%20details%20are%20needed.%0A%0AThank%20you%2C&font=Aptos&color=black"
  },
  {
    "number":"213",
    "subject":"Substation: Storm Run at Substation",
    "due_date":1759363200000,
    "days_late":2,
    "ball_in_court":"Chris Cowl (Adag Group inc.), Mesrob Arsenian (Adag Group inc.), Yervant Tutunjian (Adag Group inc.)",
    "days_in_court":"6",
    "anchor_date":"2025-09-26 11:23:00",
    "link":"https:\/\/us02.procore.com\/598134325936838\/project\/rfi\/show\/598134326895901",
    "last_reminder_date":"N\/A",
    "mailto_reminder":"mailto:?to=chrisc%40adaggroup.com%3Bmesrob%40adaggroup.com%3Byervant%40adaggroup.com&cc=aggeliki%40domacoencocorp.com%3Bkeith%40domacoencocorp.com%3Bigor%40domacoencocorp.com%3Bbbidder%40domacoencocorp.com%3Bgsilvat%40domacoencocorp.com%3Brjustice%40domacoencocorp.com&subject=RFI%20213%3A%20Substation%3A%20Storm%20Run%20at%20Substation%20%E2%80%94%20Response%20requested&body=Hi%20Chris%2C%20Mesrob%2C%20and%20Yervant%2C%0A%0AReminder%20for%20this%20RFI.%20It%20has%20been%20in%20your%20court%20for%206%20business%20day%28s%29.%0ADue%20date%3A%202025-10-02%0A%0ARFI%20link%3A%20https%3A%2F%2Fus02.procore.com%2F598134325936838%2Fproject%2Frfi%2Fshow%2F598134326895901%0A%0APlease%20let%20us%20know%20if%20any%20additional%20details%20are%20needed.%0A%0AThank%20you%2C&font=Aptos&color=black"
  },
  {
    "number":"207",
    "subject":"Substation - Fencing Under E-House on Each Face",
    "due_date":1758758400000,
    "days_late":7,
    "ball_in_court":"Jeff Burton (Eramosa International Inc.), Kyle O'Callaghan (5C Data Centers), Luc Lebel (CIMA+)",
    "days_in_court":"5",
    "anchor_date":"2025-09-29 15:06:00",
    "link":"https:\/\/us02.procore.com\/598134325936838\/project\/rfi\/show\/598134326881472",
    "last_reminder_date":"N\/A",
    "mailto_reminder":"mailto:?to=jeff.burton%40eramosa.com%3Bkocallaghan%405cdatacenters.com%3Bluc.lebel%40cima.ca&cc=aggeliki%40domacoencocorp.com%3Bkeith%40domacoencocorp.com%3Bigor%40domacoencocorp.com%3Bbbidder%40domacoencocorp.com%3Bgsilvat%40domacoencocorp.com%3Brjustice%40domacoencocorp.com&subject=RFI%20207%3A%20Substation%20-%20Fencing%20Under%20E-House%20on%20Each%20Face%20%E2%80%94%20Response%20requested&body=Hi%20Jeff%2C%20Kyle%2C%20and%20Luc%2C%0A%0AReminder%20for%20this%20RFI.%20It%20has%20been%20in%20your%20court%20for%205%20business%20day%28s%29.%0ADue%20date%3A%202025-09-25%0A%0ARFI%20link%3A%20https%3A%2F%2Fus02.procore.com%2F598134325936838%2Fproject%2Frfi%2Fshow%2F598134326881472%0A%0APlease%20let%20us%20know%20if%20any%20additional%20details%20are%20needed.%0A%0AThank%20you%2C&font=Aptos&color=black"
  },
  {
    "number":"205",
    "subject":"URGENT Phase 1.1\/1.2\/1.3 - Fiber\/Electric Drawings",
    "due_date":1758758400000,
    "days_late":7,
    "ball_in_court":"Chris Cowl (Adag Group inc.), Mesrob Arsenian (Adag Group inc.), Mouhamadou Ndoye (Exp Global Inc.)",
    "days_in_court":"2",
    "anchor_date":"2025-10-02 15:35:00",
    "link":"https:\/\/us02.procore.com\/598134325936838\/project\/rfi\/show\/598134326879079",
    "last_reminder_date":"N\/A",
    "mailto_reminder":"mailto:?to=chrisc%40adaggroup.com%3Bmesrob%40adaggroup.com%3Bmouhamadou.ndoye%40exp.com&cc=aggeliki%40domacoencocorp.com%3Bkeith%40domacoencocorp.com%3Bigor%40domacoencocorp.com%3Bbbidder%40domacoencocorp.com%3Bgsilvat%40domacoencocorp.com%3Brjustice%40domacoencocorp.com&subject=RFI%20205%3A%20URGENT%20Phase%201.1%2F1.2%2F1.3%20-%20Fiber%2FElectric%20Drawings%20%E2%80%94%20Response%20requested&body=Hi%20Chris%2C%20Mesrob%2C%20and%20Mouhamadou%2C%0A%0AReminder%20for%20this%20RFI.%20It%20has%20been%20in%20your%20court%20for%202%20business%20day%28s%29.%0ADue%20date%3A%202025-09-25%0A%0ARFI%20link%3A%20https%3A%2F%2Fus02.procore.com%2F598134325936838%2Fproject%2Frfi%2Fshow%2F598134326879079%0A%0APlease%20let%20us%20know%20if%20any%20additional%20details%20are%20needed.%0A%0AThank%20you%2C&font=Aptos&color=black"
  },
  {
    "number":"204",
    "subject":"URGENT: Phase 1.1: Route of 6\" Water Main to Pump House",
    "due_date":1758758400000,
    "days_late":7,
    "ball_in_court":"Chris Cowl (Adag Group inc.), George Gervin (Exp Global Inc.)",
    "days_in_court":"3",
    "anchor_date":"2025-10-01 14:26:00",
    "link":"https:\/\/us02.procore.com\/598134325936838\/project\/rfi\/show\/598134326873245",
    "last_reminder_date":"N\/A",
    "mailto_reminder":"mailto:?to=chrisc%40adaggroup.com%3Bgeorge.gervin%40exp.com&cc=aggeliki%40domacoencocorp.com%3Bkeith%40domacoencocorp.com%3Bigor%40domacoencocorp.com%3Bbbidder%40domacoencocorp.com%3Bgsilvat%40domacoencocorp.com%3Brjustice%40domacoencocorp.com&subject=RFI%20204%3A%20URGENT%3A%20Phase%201.1%3A%20Route%20of%206%22%20Water%20Main%20to%20Pump%20House%20%E2%80%94%20Response%20requested&body=Hi%20Chris%20and%20George%2C%0A%0AReminder%20for%20this%20RFI.%20It%20has%20been%20in%20your%20court%20for%203%20business%20day%28s%29.%0ADue%20date%3A%202025-09-25%0A%0ARFI%20link%3A%20https%3A%2F%2Fus02.procore.com%2F598134325936838%2Fproject%2Frfi%2Fshow%2F598134326873245%0A%0APlease%20let%20us%20know%20if%20any%20additional%20details%20are%20needed.%0A%0AThank%20you%2C&font=Aptos&color=black"
  },
  {
    "number":"197",
    "subject":"Substation: Conflict with Installation of Transition Boxes for Cable Busway Box Needed to be Mounted on Transformer",
    "due_date":1758240000000,
    "days_late":11,
    "ball_in_court":"Peter Frasca (Symtech Innovations USA Inc.)",
    "days_in_court":"5",
    "anchor_date":"2025-09-29 08:50:00",
    "link":"https:\/\/us02.procore.com\/598134325936838\/project\/rfi\/show\/598134326862241",
    "last_reminder_date":"N\/A",
    "mailto_reminder":"mailto:?to=peter.frasca%40symtech.com&cc=aggeliki%40domacoencocorp.com%3Bkeith%40domacoencocorp.com%3Bigor%40domacoencocorp.com%3Bbbidder%40domacoencocorp.com%3Bgsilvat%40domacoencocorp.com%3Brjustice%40domacoencocorp.com&subject=RFI%20197%3A%20Substation%3A%20Conflict%20with%20Installation%20of%20Transition%20Boxes%20for%20Cable%20Busway%20Box%20Needed%20to%20be%20Mounted%20on%20Transformer%20%E2%80%94%20Response%20requested&body=Hi%20Peter%2C%0A%0AReminder%20for%20this%20RFI.%20It%20has%20been%20in%20your%20court%20for%205%20business%20day%28s%29.%0ADue%20date%3A%202025-09-19%0A%0ARFI%20link%3A%20https%3A%2F%2Fus02.procore.com%2F598134325936838%2Fproject%2Frfi%2Fshow%2F598134326862241%0A%0APlease%20let%20us%20know%20if%20any%20additional%20details%20are%20needed.%0A%0AThank%20you%2C&font=Aptos&color=black"
  },
  {
    "number":"196",
    "subject":"Phase 1.1: 1st Floor Corridors Height Issue",
    "due_date":1759363200000,
    "days_late":2,
    "ball_in_court":"Chris Cowl (Adag Group inc.), George Gervin (Exp Global Inc.), Mouhamadou Ndoye (Exp Global Inc.)",
    "days_in_court":"1",
    "anchor_date":"2025-10-03 13:23:00",
    "link":"https:\/\/us02.procore.com\/598134325936838\/project\/rfi\/show\/598134326851928",
    "last_reminder_date":"N\/A",
    "mailto_reminder":"mailto:?to=chrisc%40adaggroup.com%3Bgeorge.gervin%40exp.com%3Bmouhamadou.ndoye%40exp.com&cc=aggeliki%40domacoencocorp.com%3Bkeith%40domacoencocorp.com%3Bigor%40domacoencocorp.com%3Bbbidder%40domacoencocorp.com%3Bgsilvat%40domacoencocorp.com%3Brjustice%40domacoencocorp.com&subject=RFI%20196%3A%20Phase%201.1%3A%201st%20Floor%20Corridors%20Height%20Issue%20%E2%80%94%20Response%20requested&body=Hi%20Chris%2C%20George%2C%20and%20Mouhamadou%2C%0A%0AReminder%20for%20this%20RFI.%20It%20has%20been%20in%20your%20court%20for%201%20business%20day%28s%29.%0ADue%20date%3A%202025-10-02%0A%0ARFI%20link%3A%20https%3A%2F%2Fus02.procore.com%2F598134325936838%2Fproject%2Frfi%2Fshow%2F598134326851928%0A%0APlease%20let%20us%20know%20if%20any%20additional%20details%20are%20needed.%0A%0AThank%20you%2C&font=Aptos&color=black"
  },
  {
    "number":"124",
    "subject":"Substation - Response to RFI #101: Design to correct Sump Vault Pump Problem in Substation",
    "due_date":1750118400000,
    "days_late":75,
    "ball_in_court":"Jeff Burton (Eramosa International Inc.), Kyle O'Callaghan (5C Data Centers), Sarah Devare Paquet (CIMA+)",
    "days_in_court":"9",
    "anchor_date":"2025-09-23 19:29:00",
    "link":"https:\/\/us02.procore.com\/598134325936838\/project\/rfi\/show\/598134326622235",
    "last_reminder_date":"N\/A",
    "mailto_reminder":"mailto:?to=jeff.burton%40eramosa.com%3Bkocallaghan%405cdatacenters.com%3Bsarah.devarepaquet%40cima.ca&cc=aggeliki%40domacoencocorp.com%3Bkeith%40domacoencocorp.com%3Bigor%40domacoencocorp.com%3Bbbidder%40domacoencocorp.com%3Bgsilvat%40domacoencocorp.com%3Brjustice%40domacoencocorp.com&subject=RFI%20124%3A%20Substation%20-%20Response%20to%20RFI%20%23101%3A%20Design%20to%20correct%20Sump%20Vault%20Pump%20Problem%20in%20Substation%20%E2%80%94%20Response%20requested&body=Hi%20Jeff%2C%20Kyle%2C%20and%20Sarah%2C%0A%0AReminder%20for%20this%20RFI.%20It%20has%20been%20in%20your%20court%20for%209%20business%20day%28s%29.%0ADue%20date%3A%202025-06-17%0A%0ARFI%20link%3A%20https%3A%2F%2Fus02.procore.com%2F598134325936838%2Fproject%2Frfi%2Fshow%2F598134326622235%0A%0APlease%20let%20us%20know%20if%20any%20additional%20details%20are%20needed.%0A%0AThank%20you%2C&font=Aptos&color=black"
  }
]